README.md
setup.py
healthcheck/__init__.py
healthcheck/actions.py
healthcheck/admin.py
healthcheck/api.py
healthcheck/auth.py
healthcheck/plugin.py
healthcheck/storage.py
healthcheck/backends/__init__.py
tests/backends/__init__.py
tests/backends/test_zabbix.py
tsuru_hcaas.egg-info/PKG-INFO
tsuru_hcaas.egg-info/SOURCES.txt
tsuru_hcaas.egg-info/dependency_links.txt
tsuru_hcaas.egg-info/requires.txt
tsuru_hcaas.egg-info/top_level.txt