Metadata-Version: 1.1
Name: tsuru-hcaas
Version: 0.3.0
Summary: Healthcheck as a service API for Tsuru PaaS
Home-page: UNKNOWN
Author: Tsuru
Author-email: tsuru@corp.globo.com
License: UNKNOWN
Platform: UNKNOWN
Classifier: Programming Language :: Python :: 2.7
